{"House": 142, "Electro House": 41, "Progressive House": 26, "Pop": 1633, "Electronica": 147, "Gospel": 207, "R&B": 574, "Alternative Rock": 835, "Hip Hop": 661, "Soul": 387, "Hard Rock": 471, "J-Pop": 39, "J-Rock": 15, "Rock": 1864, "Dance-Pop": 42, "Synthpop": 230, "Nu-Disco": 5, "Disco": 94, "New Jack Swing": 13, "Acoustic": 122, "Grime": 15, "Folk": 809, "Funk Rock": 19, "Neo Soul": 19, "Pop Rock": 490, "Soft Rock": 75, "Alternative Metal": 149, "Electronic Rock": 61, "Nu Metal": 62, "Rap Metal": 21, "Teen Pop": 28, "Grunge": 45, "Glam Rock": 55, "Progressive Rock": 319, "Electropop": 87, "Indie Pop": 368, "Folktronica": 6, "Dance": 228, "Downtempo": 25, "Trip Hop": 61, "Country": 485, "Country Pop": 11, "Heavy Metal": 529, "Reggae": 146, "Ska": 65, "Rocksteady": 3, "Glam Metal": 49, "Electronic": 607, "Latin": 79, "Power Pop": 101, "Blues Rock": 168, "Pop Punk": 146, "Blues": 617, "Rock 'N' Roll": 133, "Post-Punk": 110, "Indie Rock": 712, "Techno": 75, "New Age": 43, "French House": 11, "Thrash Metal": 117, "Psychedelic Rock": 152, "Space Rock": 20, "Classic Rock": 41, "Punk Rock": 412, "Dubstep": 63, "Experimental": 113, "Britpop": 39, "Eurodance": 63, "Country Rock": 71, "EDM": 36, "Trance": 68, "Funk": 165, "Jazz": 484, "Baroque Pop": 34, "Post-Grunge": 67, "Trap": 9, "East Coast Hip Hop": 5, "Art Rock": 67, "Post-Punk Revival": 18, "Rap Rock": 16, "Gothic Rock": 75, "Emo": 62, "Piano Blues": 16, "Brazilian": 209, "Sertanejo": 48, "Vocal": 84, "Rockabilly": 57, "Memphis Blues": 18, "New Wave": 199, "Crunk": 4, "Southern Hip Hop": 5, "Jangle Pop": 14, "College Rock": 8, "Latin Pop": 37, "Bachata": 2, "Reggae Fusion": 8, "Rapcore": 9, "Dance-Rock": 6, "Vocal Jazz": 61, "Europop": 17, "Eurobeat": 3, "Folk Rock": 313, "Swing": 72, "Bossa Nova": 85, "Classic Pop": 14, "Breakbeat": 13, "Electropunk": 10, "Big Beat": 6, "Crossover": 6, "Alternative Hip Hop": 37, "Psychedelic Pop": 24, "Soundtrack": 40, "Singer-Songwriter": 755, "World Music": 118, "Deep House": 28, "Adult Contemporary": 66, "Gangsta Rap": 8, "West Coast Hip Hop": 4, "Funk Melody": 15, "Funk Carioca": 11, "MPB": 219, "Quiet Storm": 4, "Pagode": 17, "Salsa": 18, "Deathrock": 6, "Hardcore Punk": 157, "Classical": 94, "Speed Metal": 27, "Industrial Metal": 86, "Neue Deutsche H\u00e4rte": 21, "Protest Song": 64, "Funk Metal": 18, "Alternative Country": 90, "Roots Rock": 32, "Metalcore": 221, "Ax\u00e9": 15, "Samba-Reggae\u200e": 1, "Indie": 70, "Dancehall": 20, "Dixieland": 11, "Big Band": 27, "Samba": 122, "French Hip Hop": 4, "Avant-garde": 45, "Industrial Rock": 125, "Shock Rock": 8, "Acid Rock": 7, "Melodic Metalcore": 8, "Groove Metal": 34, "Electric Blues": 44, "Chicago Blues": 49, "Electro": 114, "Progressive Metal": 143, "Garage Rock": 87, "Future Garage": 3, "Brazilian Rock": 59, "Psychedelic": 25, "Country Blues": 86, "Talking Blues": 2, "Detroit Blues": 2, "French Pop": 33, "Dance Punk": 18, "Dream Pop": 70, "Stoner Rock": 31, "Baroque": 3, "Indietronica": 16, "Bluegrass": 92, "Bebop": 19, "Cool Jazz": 8, "Children's Music": 33, "Easy Listening": 42, "Indie Folk": 117, "Deathcore": 77, "Electronicore": 29, "Post-Hardcore": 188, "Symphonic Metal": 74, "Melodic Hardcore": 37, "Rock en Espa\u00f1ol": 6, "Ballad": 135, "IDM": 17, "Power Metal": 125, "Francophone": 18, "Bolero": 11, "Latin Jazz": 4, "Trad Jazz": 10, "Tech House": 19, "Southern Rock": 47, "Swamp Rock": 7, "Ska Punk": 28, "Banda": 4, "Opera": 15, "Flamenco": 15, "Sambalan\u00e7o": 3, "Tropicalismo": 17, "Rumba": 3, "Son Cubano\u200e": 1, "Drum And Bass": 38, "Reggaeton": 17, "Minimal": 10, "Downbeat": 3, "Forr\u00f3": 15, "Christian Hip Hop": 12, "Smooth Jazz": 12, "Blue-Eyed Soul": 18, "Chanson": 226, "Death Metal": 143, "Schlager": 152, "Chamber Music": 2, "Protopunk": 6, "Y\u00e9-y\u00e9": 2, "Experimental Rock": 93, "Jovem Guarda": 13, "Contemporary R&B": 5, "Gothic Metal": 80, "Symphonic Rock": 35, "Acid Jazz": 14, "Deutschrock": 28, "Christian Rock": 137, "Christian Metal": 44, "Volkst\u00fcmlich": 1, "Industrial": 290, "Patchanka": 1, "Ranchera": 6, "Norte\u00f1o\u200e": 2, "Spoken Word": 88, "Jazz Fusion": 80, "Latin Rock": 21, "Lo-Fi": 46, "Delta Blues": 50, "Musical": 32, "Norte\u00f1o": 6, "Noise Rock": 32, "Garage Punk": 5, "Hard Trance": 3, "Midwest Rap": 4, "Orchestral": 8, "Hardstyle": 4, "Surf Rock": 19, "Religious": 59, "Nasheed": 1, "Brega": 15, "New Rave": 4, "Ambient": 91, "Post-Rock": 41, "Instrumental Rock": 22, "Hard Bop": 4, "Post-Thrash": 2, "Melodic Death Metal": 73, "Texas Blues": 9, "Disco House": 3, "Celtic": 38, "Morna": 1, "Gothic": 27, "Dark Wave": 52, "Drumstep": 6, "Vocal Trance": 1, "Acid Techno": 4, "Art Punk": 3, "Drone Music": 7, "Romantic": 4, "Vocalese": 11, "Sludge Metal": 20, "Mariachi": 3, "Boogie": 9, "Harmonica Blues": 41, "Krautrock": 13, "K-Pop": 13, "Roots Reggae\u200e": 2, "Worship": 58, "Contemporary Christian": 114, "Trova": 2, "Symphonic Black Metal": 11, "Cajun": 4, "Mod Revival": 1, "Outlaw Country": 7, "Post-Bop": 6, "Horror Punk": 16, "Arena Rock": 4, "Celtic Punk": 5, "Glitch": 8, "Psychedelic Trance": 1, "Brutal Death Metal": 7, "Bai\u00e3o": 7, "Freak Folk": 8, "Piano Rock": 10, "Anti-Folk": 7, "Candombe": 4, "Hip House": 1, "Dub": 23, "Third Stream": 5, "West Coast Jazz": 5, "Tejano": 6, "Grupero": 2, "Progressive Death Metal": 5, "Italian Folk": 16, "Afrobeat": 4, "Highlife": 1, "Screamo": 12, "Skate Punk": 6, "Technical Death Metal": 15, "Calypso": 5, "Comedy": 175, "Soca": 3, "Boogie Woogie": 23, "Underground Hip Hop": 20, "Progressive Trance": 4, "Rave": 6, "Jazz Rap": 5, "Art Pop": 3, "Black Metal": 97, "Folk Metal": 34, "Sophisti-Pop": 2, "Punk Blues": 4, "Psych Folk": 4, "Comedy Rock": 10, "Cowpunk": 6, "Operatic Pop": 5, "Mathcore": 22, "Samba-Reggae": 1, "Progressive Folk": 4, "Americana": 59, "Christian Hip Hop\u200e": 5, "Hindustani Classical": 1, "Samba De Roda": 1, "Andean Music": 2, "Hardcore Hip Hop": 3, "Yoruba Music": 1, "Irish Folk": 14, "Neoclassical": 15, "Jump Blues": 24, "Pop-Rap": 14, "Alternative Dance": 17, "Rock Opera": 4, "Cumbia": 12, "Sean-N\u00f3s": 1, "Doo-wop": 16, "Soul Blues": 8, "Jazz Blues": 4, "Political Hip Hop": 5, "Queercore": 3, "Zouk": 3, "Cabaret": 37, "Contemporary Jazz": 2, "Pop-Folk": 4, "Neo-Psychedelia": 9, "Indian Classical Music": 2, "Choro": 2, "Mandopop": 2, "Neue Deutsche Welle": 23, "Minimal Techno": 4, "G-Funk": 4, "Doom Metal": 60, "Southern Metal": 4, "Samba-Rock": 2, "Blues Revival": 5, "Shoegazing": 31, "Folk Punk": 9, "Tango": 5, "Cuarteto": 1, "Grindcore": 24, "Goregrind": 1, "Death 'n' Roll": 2, "Swamp Blues": 8, "Louisiana Blues": 7, "Deutschpunk": 15, "Pirate Metal": 1, "Heartland Rock": 4, "Medieval": 20, "Sunshine Pop": 6, "Roots": 19, "Progressive Country": 2, "Regional Mexican": 1, "Duranguense": 2, "Electroclash": 9, "Chillwave": 8, "Acid House": 9, "Christmas": 6, "Anime": 4, "Soundtrack/Television": 2, "Soundtrack/Anime": 3, "Nashville Sound": 5, "Avant-garde Metal": 15, "Djent": 10, "French Hip Hop\u200f\u200e": 1, "Jam Band": 14, "Mbalax": 1, "Ragga": 3, "Viking Metal": 12, "Grindie": 1, "Christian": 42, "Honky Tonk": 14, "Neofolk": 30, "Parody": 53, "Dark Cabaret": 8, "Beat": 16, "Noise Pop": 8, "Jazz Fusion\u200e": 1, "Christian Punk": 9, "Crossover Thrash": 3, "Bubblegum Pop": 8, "Kwaito": 1, "Neue Deutsche Todeskunst": 2, "Samba-Can\u00e7\u00e3o": 4, "Celtic Rock": 9, "Neo-Classical Metal": 9, "Enka": 1, "Corrido": 1, "New Orleans Rhythm and Blues": 4, "Old School Hip Hop": 2, "Post-Industrial": 8, "Pagan Metal": 8, "Jazz-Funk": 6, "Proto Rap": 2, "Glitch Hop": 2, "Extreme Metal": 7, "Noise": 13, "Breakcore": 4, "Digital Hardcore": 4, "Gospel Blues": 5, "Piedmont Blues": 19, "East Coast Blues": 11, "Punk Cabaret": 2, "Nu Jazz": 6, "EBM": 114, "Aggrotech": 22, "Power Noise": 4, "Adult Contemporary\u200e": 1, "Fado": 6, "Country Rap": 1, "Post-Metal": 11, "Gypsy Jazz": 1, "Skiffle": 7, "Post-Britpop": 3, "Gypsy": 5, "Dark Ambient": 14, "Children's Music\u200e": 3, "No Wave": 4, "Visual Kei": 5, "Hawaiian": 5, "A Cappella": 12, "Experimental Hip Hop": 2, "Swing Revival": 4, "Slowcore": 11, "Italo Disco": 22, "Rock 'N' Roll\u200e": 2, "British Invasion": 8, "Slam": 1, "Western Swing": 10, "A Cappella\u200e": 1, "Ragtime": 12, "Zeuhl": 1, "St. Louis Blues": 4, "Roots Reggae": 2, "Free Jazz": 5, "Freestyle": 115, "Bhangra": 2, "Gypsy Punk": 2, "Math Rock": 11, "Urban Contemporary": 2, "Austropop": 10, "Anarcho-Punk": 8, "Crust Punk": 6, "Sufi": 1, "Raggamuffin": 1, "Canterbury": 15, "Avant-Pop": 4, "Soundtrack/Movie": 20, "Soundtrack/Musical\u200e": 2, "Psychobilly": 8, "Ethereal Wave": 6, "Hamburger Schule": 9, "Funky House": 1, "Volkslied": 30, "Horrorcore": 4, "Spanish Rock": 3, "Old-time Music": 23, "Drone Doom": 3, "Electropop\u200e": 2, "Futurepop": 23, "2-tone": 1, "Reggae Rock": 2, "Soundtrack/Musical": 11, "Scat": 1, "Riot Grrrl": 3, "Dark Metal": 10, "Liquid Funk": 1, "Chiptune": 4, "Shoegazing\u200e": 1, "Dark Electro": 11, "Andalusian Rock": 2, "Volksmusik": 5, "Lambada": 2, "Goa Trance": 1, "Contemporary Folk": 7, "Persian": 3, "Neo-Progressive Rock": 3, "Motown": 3, "Zydeco": 4, "Street Punk": 4, "Shoegazing\u200f\u200e": 1, "Punk Jazz": 2, "M\u00fasica Popular Portuguesa": 1, "Dark Atmospheric": 1, "Happy Hardcore": 8, "Oi-Punk": 6, "Nintendocore": 2, "Novelty": 7, "Balearic Beat": 2, "Hi-NRG": 7, "Steampunk": 4, "NSBM": 1, "Progressive Bluegrass": 8, "Pub Rock": 5, "Modern Classical": 4, "Powerviolence": 2, "Bakersfield Sound": 2, "Beatbox": 1, "Gothic Rock\u200f\u200e": 2, "Electronic Rock\u200e": 1, "Nerdcore Hip Hop\u200e": 1, "Electric Folk": 2, "Dance-Pop\u200e": 1, "Electro Swing": 1, "Unblack Metal": 1, "Soundtrack/Movie\u200e": 1, "Progressive Rock\u200e": 2, "Progressive Rock\u200f\u200e": 1, "Junkanoo": 1, "Drum And Bass\u200e": 1, "Euro Disco": 3, "Latin Hip Hop": 2, "Gabber": 2, "Nueva canci\u00f3n": 1, "Urban Contemporary Gospel": 1, "Chill-out": 1, "Barbershop": 3, "Nederpop": 1, "Klezmer": 5, "Electro-Industrial": 2, "Swiss Rock": 1, "Bandanejo": 3, "RIO": 3, "Christian Ska": 2, "Western": 3, "Psychedelic Folk": 2, "Lounge Music": 2, "Soul Jazz": 1, "Lo-Fi\u200e\u200e": 1, "Symphonic Metal\u200e": 1, "West Coast Blues": 3, "Renaissance": 1, "Minnesang": 6, "Persian Traditional": 1, "Humppa": 1, "Raw Rock": 1, "Satire": 4, "Dream Trance": 1, "String Band": 1, "Outsider Music": 2, "Post Rock": 2, "Native American": 1, "Indie Folk\u200e": 1, "Singer-Songwriter\u200e": 2, "Modern Laika": 1, "Hip Hop Soul": 1, "Coldwave": 13, "Neofolk\u200f\u200e": 1, "Dance Punk\u200e": 1, "Post-Disco": 1, "Post-Grunge\u200f\u200e": 2, "Sung Poetry": 1, "Bubblegum Dance": 1, "Surf": 2, "Martial Industrial": 1, "Hard Rock\u200e": 1, "Milonga": 1, "Gstanzl": 1, "Polka": 2, "Contemporary Christian\u200e": 2, "Speedcore": 1, "Military Music": 1, "Dirty Blues": 11, "Australian Hip Hop": 1, "Progg": 2, "Soft Rock\u200e": 1, "Miami Bass": 1, "Dark Wave\u200f\u200e": 1, "Alpine New Wave": 1, "Country Rock\u200e": 1, "Shibuya-Kei": 1, "Alternative Rock\u200e": 1, "Palingsound": 1, "Crack Rock Steady": 1, "Sea Shanties": 1, "Pirate Band": 1, "Rock\u200e": 1, "Jug Band": 3, "Vaudeville": 6, "Symphonic Rock\u200e": 1, "Neo-Psychedelia\u200f\u200e": 1, "Ska Punk\u200e": 1, "Noha": 1, "Nerdcore Hip Hop": 1, "Synthpop\u200e": 1, "Electro\u200e": 1, "Southern Gospel": 1, "Worldbeat": 1}